dino/__init__.py
dino/dino.py
dinocore-0.1.dist-info/LICENSE
dinocore-0.1.dist-info/METADATA
dinocore-0.1.dist-info/WHEEL
dinocore-0.1.dist-info/top_level.txt
dinocore-0.1.dist-info/RECORD
