Metadata-Version: 2.1
Name: dinocore
Version: 0.1
Summary: dynamic config management tool
Author: Alp Sakaci
Author-email: erenalpsakaci@gmail.com
Requires-Python: >=3.6
License-File: LICENSE
Requires-Dist: PyYAML==6.0.2
